{"5-semester":{"keywords":["femte","semester","er","startet","dette","har","jeg","valgfag","-","introduktion","til","machine","learning","og","data","mining","big","samt","obligatoriske","fag","basismat","videregående","matematik","diplomingeniører","innovation","pilot","glæder","mig","lære","om","grundlæggende","*data","science*","håber","på","kunne","implementere","en","masse","fede","ml","projekter","løbet","af","semesteret","måske","med","inovativt","twist","nu","må","vi","se","hvor","inovativ","bliver","efter","piloten","post","Inovation"],"name":"Femte semester"},"autonom-drone":{"keywords":["opgaven","var","lave","noget","softeware","til","en","drone","som","skulle","gøre","den","istand","autonomt","kunne","flyve","gennem","seks","røde","ringe","med","qr-koder","vi","anvendte","java","bibliotektet","yadrone","samt","computer","vision","opencv","analysere","videofeeden","fra","droen","på","og","ud","de","data","få","af","billedet","sende","komandoer","dronen","projektet","er","udarbjedet","gruppe","kode","kan","findes","[her](https://github.com/tMascagni/CDIO_3)","post","project","DTU"],"name":"Autonom drone"},"chess":{"keywords":["post","project"],"name":"Implementing a Chess game and a simple artificial intelligence - Part 1"},"dtu-grade-viewer-pwa":{"keywords":["pwa","dtu","student","login","number","inside","password","information","logged","app","easy","keeping","track","grades","choose","program","gpa","futhermore","view","details","grade","open","overview","screen","show","lowest","received","avg","highest","fund","server","spin","page","means","slow","opening","solution","expensive","installed","browser","ios","android","post","project","DTU"],"name":"GPA for DTU students - PWA"},"dtu-ios-grad-viewer":{"keywords":["appen","gør","det","muligt","se","en","liste","alle","karaktere","givet","på","udannelse","ved","danmarks","tekniske","universitet","nem","både","derudover","kan","man","hvorvidt","karakteren","er","bekræftet","ects","points","og","udregning","af","vægtet","gennemsnit","ud","fra","kursernes","omfang","appe","skrevet","swift","køre","kun","apples","enheder","med","ios","koden","finde","[her](https://github.com/trolund/DTUGradViewer).","post","project","DTU"],"name":"Karaktergennemsnit udregning - IOS app"},"dtu-meeting-ios":{"keywords":["projektet","består","af","en","ios","app","skrevet","swift","appen","skal","gøre","det","muligt","brugeren","nemt","kan","give","feedback","efter","møder","undervisning","og","andre","sammenhænge","hvor","vil","være","brugbart","kunne","modtage","kort","tid","endt","session","dette","gør","har","brugere","derved","opdelt","dele","der","bruger","som","ikke","behøver","login","blot","skulle","til","den","anden","brugertype","mødeafholderen","med","tilknytning","virksomheds","id","denne","bruge","oprette","starte","gerne","bedste","mulighed","forbedre","mødestruktur","formidling","samt","evaluere","på","forståelse","præsenterede","materiale","bidrage","færre","unødige","mere","relevant","indhold","formidlet","bedst","givende","målgruppe","opnå","bliver","kurset","distribuerede","systemer","sideløbende","udviklet","restful","backend","persistent","datalag","form","firebase","database","post","project","DTU"],"name":"Møde feedback - IOS app"},"innovations":{"keywords":["fed","afslutning","på","vores","innovations","projekt","med","en","anerkendelse","arbejde","pitch","vandt","de","andre","projekter","og","kun","enkelt","point","fra","det","maximalt","opnåelige","tak","til","thomas","kainø","jensen","muligheden","@bocart","resten","af","gruppen","daniel","davidsen","malene","gravlund","sørensen","olga","lubbers","jakob","mølhave","godt","samarbejde","den","kommende","3-ugers","periode","glæder","jeg","mig","faget","introduktion","koordinering","fordelte","applikationer","hvor","derforhåbeligt","skal","laves","multiplayer","spil","så","nok","blive","sjov","post"],"name":"6. semester"},"instruction-set-simulator":{"keywords":["##","introduction","article","describes","implemented","basic","risc-v","instruction","set","simulator","implements","**rv32i**","instructions","simulated","features","pipelining","architectural","elements","due","scope","project","part","computer","architecture","engineering","dtu","means","focus","gaining","knowledge","general","limited","experience","programing","assembly","language","proved","quiet","fun","leaning","found","pages","*","https://msyksphinz-self.github.io/riscv-isadoc/html/rvi.html#lbu","https://itnext.io/risc-v-instruction-set-cheatsheet-70961b4bbe8","design","built","roughly","follow","flow","real","processor","execute","program","single","cycle","manner","designed","operate","little-endian","system","starts","sets","starting","state","machine","includes","making","pc","allocates","space","registers","array","mb","memory","consist","bit","signed","integer","int","data","type","java","time","handle","unsigned","conversion","made","represented","byte","addressed","8-bit","bytes","load","lb","position","half","word","16-bit","loaded","32-","extract","32-bit","values","parts","combined","bit-wise-or","0x0","reserved","segment","text","area","initialized","instantiated","ready","running","multiple","programs","shutting","leave","work","loads","immediately","static","expected","formats","types","sb","uj","order","entry","loading","handled","separate","class","core","loop","handles","evaluated","steps","fetch","step","represent","decode","divide","fields","intermediate","func3","func7","ect","based","format","opcode","executes","mutate","case","counters","problem","raise","exception","printing","current","debugger","mode","end","exit","code","instance","unsupported/unimplemented","attempted","executed","calling","ecall","setting","a7","=","default","settings","apply","make","compatible","test","venus","ripes","incorporate","print","information","console","counter","base","specific","printreg","flag","equal","true","implementation","section","outline","written","openjdk","simple","cli","developed","easy","run","###","input","output","loader","simply","logic","provided","binary","files","functionality","method","reads","file","called","readbinfile","returns","read","four-byte","chunks","readint","open","datainputstream","reading","discovered","bits","stored","big-endian","reversed","change","architectures","writing","contents","x0-x31","belongs","datadumper","decoder","decoded","responsibility","instructiondecoder","map","object","representing","extracted","constructor","shifting","place","mask","field","classes","encapsulate","inherited","abstract","polymorphic","complexity","named","isasimulator","mutating","consists","length","0x100000","makes","total","size","expect","amount","mem-","ory","allocated","correctly","javas","converted","conversions","small","auxiliary","functions","improve","read-","ability","convert","integers","sign-extensions","runprogram","takes","optionally","fetch-decode-execute","practice","condition","variable","boolean","stop","happen","ways","ordinary","valid","error","provide","ex-","tracted","exeinstr","call","business","func","resolve","witch","action","preform","x0","register","easiest","ensure","store","effect","future","execution","consistent","instrcount","incremented","debugging","purposes","arithmetic","logical","implement","group","simulates","computations","alu","*addi*","destination","-","source","rs1","imm","added","cases","*sltiu*","treated","numbers","branch","enables","deviate","strictly","sequential","changing","branch-","ing","subtracting","rv32i","usage","easier","produce","artifact","rv32ijar","user","tool","compiled","jar","*rv32ijar*","-cp","picocli-470jarrv32ijar","produced","number","options","command","--help","result","info","[-dhpruv]","[-e=]","[-er=]","supporting","path","bin","-d","--debug","debug","false","-e","--ecall=","decide","kind","env","-er","--ecallreg=","a0","-h","show","message","-p","--print","-r","--result","-u","--dump","write","data-dump","-v","--version","version","discussion","structure","extended","substantial","refactoring","executing","located","optimized","performance","readability","simplicity","closely","match","hardware","components","higher","abstraction","model","chosen","choosing","yielded","benefits","beneficial","simulate","sophisticated","avoid","adaptation","lan-","guage","richer","variations","early","development","process","frequently","correctness","implemen-","tation","assignment","evaluate","unit","testing","framework","junit","start","converge","91%","measured","percentages","lines","tested","errors","add","negative","simplify","utility","results","res","contained","comparing","task","passed","dump","feature","dump-files","####","config","flags","configuration","simulators","#####","ecallreg","[venus","docs](https://github.com/kvakil/venus/wiki/Environmental-Calls)","[ripes","docs](https://github.com/mortbopet/Ripes/blob/master/docs/ecalls.md)","2022-08-18","runtime","environment","build","18021+1-1","64-bit","server","vm","mixed","sharing","tests","|","✅/❌️","|---------------|------------|------|","✅","addneg","addpos","addlarge","shift2","bool","shift","branchcnt","branchmany","branchtrap","string","width","recursive","t1","t2","t3","t4","t5","t6","t7","t8","t9","t10","t11","t12","t13","t14","t15","conclusion","successfully","meets","requirements","implementing","joyful","learning","familiar","isa","contact","interested","project","DTU"],"name":"RISC-V Instruction Set Simulator"},"microservices":{"keywords":["##","introduction","repository","source","code","deliverables","group","software","development","web","services","held","january","technical","university","denmark","dtu","system","consists","microservices","called","payment-service","token-service","account-service","report-service","rest","interfaces","giving","interface","exists","client","application","executing","end-to-end","tests","###","content","-","[introduction]#introduction","[content]#content","[microservices]#microservices","[rest]#rest","[payment-service]#payment-service","[token-service]#token-service","[account-service]#account-service","[report-service]#report-service","[client-application]#client-application","[openapi]#openapi","[installation]#installation","[contributors]#contributors","**the","longer","running**","running","virtual-machine","compute","base","url","`g-11computedtudk`","main","listening","port","`8080`","accessing","`g-11computedtudk8080`","report","service","managerial","purposes","found","`8083`","access","swagger","ui","appending","`/swagger-ui`","end","overview","diagram","project","holds","unified","essentially","http","request","map","respective","rabbitmq","message","internal","purpose","execute","money","transfers","fastmoney","bank","regular","payments","refunds","triggered","customer","tokens","merchant","behalf","payment","situation","functionality","situations","validate","token","account","track","user","accounts","exist","dtupay","interacts","3rd","party","bankservice","controls","management","generate","reports","customers","merchants","managers","messages","succeeded","records","reporting","client-application","attempts","emulate","actual","usage","simulations","applications","openapi","fetch","specification","curl","command","change","interfance","specifications","root","`openapi-spec-dtupay-apiyml`","`openapi-spec-management-api`","```","-o","openapi-specyml","g-11computedtudk8080/openapi","installation","build","install","locally","docker","script","docker-compose","required","build_and_runsh","package","containers","configure","run","`mvn_package_allsh`","building","executable","binaries","desirable","contributors","tobias","rydberg","s173899","sebastian","lindhard","budsted","s135243","daniel","larsen","s151641","emil","kosiara","s174265","troels","lund","s161791","kasper","stilling","s141250","post","project","DTU"],"name":"Microservices project"},"motion-detection-camera":{"keywords":["en","opgave","som","blev","stillet","faget","programmering","koden","anvender","det","kamera","er","default","system","køre","på","de","billeder","kameraet","opfage","sammenligner","vi","par","og","med","opencv","identificere","hvor","der","sket","ændringer","billedet","derved","bevægesle","hvis","tilstrækkelig","meget","bevægelse","inden","interval","5sek","gemmes","billede","tidsstempel","enheden","post","project","DTU"],"name":"Motion detection camera"},"movie-guns":{"keywords":["opgaven","var","lave","en","app","til","android","som","skulle","kunne","styre","atrapvåben","filmindusrien","dette","betød","man","monitorere","armonition","antal","skud","batteri","niveau","samt","aktivere","og","deaktivere","våbnet","derudover","gruppere","våbene","give","dem","navne","slut","produktet","blev","motificering","af","allrede","eksiterene","kode","microkontroller","således","den","kontaktes","wifi","kan","video","hvor","jeg","demoer","appen","lige","inden","vi","skal","eksamen","forsvare","stillet","[cph","industries](https://cph.industries/).","post","project","DTU"],"name":"App til at kontrollere atrap film våben"},"package-delivery":{"keywords":["model-based","systems","engineering","-","simulating","futuristic","package","delivery","service","drones","project","part","dtu","fall","video","running","simulator","found","[here.](https://youtu.be/Zj8hlKBSeCk)","simulation","environments","consist","randomly","generated","neighborhoods","lands","houses","designated","addresses","futhermore","number","delivering","packages","truck","sorted","based","distances","distinction","drone","carry","time","follow","pattern","fetching","fly","address","drop","arrival","return","implementation","layout","environment","represented","𝑁","×","𝑀","matrix","parts","defined","characters","*","road","ground","spot","translated","graphical","representation","render","items","screen","means","object","world","coordinates","match","positions","changed","main","config","file","**configini**","global","parameters","configuration","offers","great","amount","flexibility","customize","scenario","instance","input","world_size=15","ground_size=5","road_size=1","customer_density=05","result","neighborhood","called","code","kan","configured","move","applying","path-finder","route","added","marked","character","started","moving","deliver","pre-computed","clusters","starting","cluster","**a**","**c**","extensive","logging","important","*fly","times*","*distance","traveled","drones*","ui","controlled","keys","pressing","zoom","arrow","explore","###","show","version","weeks","hand-in","contributors","oda","byskov","aggerholm","indre","aruodziute","anders","skrøvseth","haugen","troels","lund","jens","dieter","kjær","modvig","william","wulff","post","project","DTU"],"name":"Simulating - Package Delivery using Drones in urban areas"},"personal-website":{"keywords":["article","describes","experience","nextjs","headless","cms","content","management","system","project","started","**eleven**","latest","greatest","updated","**d**","time","writing","**f**","release","bu","moment","remain","version","chosen","simply","previous","found","developer","quiet","joyful","post","project"],"name":"Personal website with Next.js and headless CMS"},"ping-pong-game":{"keywords":["dette","er","helt","simplet","ping","pong","spil","personer","samt","singleplayer","mode","hvor","man","kan","spille","mod","computeren","på","fire","forskelige","niveauer","spillet","udviklet","javascript","med","biblioteket","phaser","det","muligt","prøve","en","deomen","online","[her](https://trolund.github.io/JSPingPongGame/).","post","project"],"name":"Ping pong"},"tank-game":{"keywords":["part","**introduction","coordination","distributed","applications**","dtu","application","tuple","spaces","implemented","project","battle","tank","java-based","game","inspired","ongoing","trouble-series","simplicity","deathmatch-style","players","attempt","shoot","ricocheting","shells","flying","place","hosts","individual","starting","places","map","angles","corners","maneuver","position","angle","hit","hiding","corner","player","realises","dodge","incoming","shell","shooting","air","resort","maps","25x25","tile","2d-map","desert","theme","decided","static","procedurally","generated","allowed","create","fair","distribution","obstacles","decorative","foliage","stones","themes","communication","data","transfer","handled","tuples","java","library","jspace","system","utilises","server/client-based","structure","runs","server","connected","transmits","current","actions","server-based","space","simulates","real","time","sends","updates","state","listens","local","final","product","flaws","functions","original","inspiration","positions","directions","received","transmitted","leaving","jittering","official","github","repository","public","interested","note","pspace-dependencies","maven","installed","functioning","order","run","properly","###","video","contributors","-","arvid","langsø","mads","stege","peter","el-habr","simon","engquist","troels","lund","**the","code","found","[here](https://github.com/STAMP-Team19/BattleTank).**","post","project"],"name":"Multiplayer Tank game"},"tower-defense":{"keywords":["spillet","blev","til","grundklægende","tower","defence","spil","med","tre","typer","af","tårne","samt","fjener","baner","blive","modeller","som","2d","array","karaktere","*","-","en","platform","tårne","kan","stå","på","tomt","rum","hvor","fjender","bevæge","sig","tea","start","position/instansierings","punkt","slut","punkt/punkt","fjenden","skader","spilleren","og","forsvinder","selve","instantieringen","banen","foregår","ved","vi","iterere","gennem","arrayet","switch","evaluere","hver","enkelt","karakter","mappe","dem","enten","instantiere","givent","gameobject","vores","3d","verden","eller","tilføje","denne","position","være","område","betrædes","fjenderne","tårn","har","rækkevide","helvist","bestemes","tårntypen","upgraderings","nivuet","tårnene","møder","finde","fejener","den","skyder","på","nærmeste","er","længest","der","også","lavet","undertyper","nedarver","fra","enemy","klassen","det","blevet","henblik","lave","forskellige","styrker/svagheder","​evner​","skal","kunne","navigere","igennem","bane","anvender","bredde-først","søgnings","algoritmen","vej","de","gå","[]/assets/blog/old/tower1png","post","project","DTU"],"name":"Tower defense spil"},"noise-filtering":{"keywords":["dette","post","er","udsnit","af","en","opgave","jeg","lavet","som","del","kurset","distribuerede","og","parallelle","systemer","på","dtu","foråret","andvendte","_c_","det","primærer","programerings","sprog","derudover","bliv","blev","der","anvendt","forskilige","api'er","til","parallel","programering","disse","var","openmp","brugt","shared-memory","programming","altså","model","hvor","flere","tråde","tilgår","samme","memory","space","individuelt","kan","udføre","sin","delvist","eller","fuldstænding","uafhængigt","de","andre","række","billeder","med","støj","blevet","udleveret","eksemple","sådan","billede","blive","set","neden","[alt","text]/assets/blog/noise-filtering/pocket_watchbmp","øvelsen","gik","ud","reducer","mængden","dernæst","parallelisere","programmet","ved","hjælp","selv","efter","filteret","andvendt","så","dermed","text]/assets/blog/noise-filtering/pocket_watch-processedbmp","den","**ikke**","paralleliseret","kode","ses","```c","/*","functions","calculates","average","filter","parameterizable","window","n*n","*/","void","averagingfilternaivepixel_array*","img","pixel_array*","orig_img","int","{","red_avg","blue_avg","green_avg","radius","out_of_bounds","idx","curr_idx","int32_t","pixel","%","==","printferror","odd","sized","window\\n","exit1","}","=","/","sizey","i++","sizex","j++","pixels","extend","bounds","count","amount","miss","size","smaller","rgb","values","loop","sums","-","img->sizey","||",">=","img->sizex","out_of_bounds++","continue","+","*","shift","mask","add","+=","orig_img->data[idx]",">>","0xff","divide","total","sum","/=","current","data[curr_idx]","```","algoritmen","håndterer","tæt","kanten","billedeområdet","undgå","arbejdede","median","funktionen","står","finde","indekset","vektor-median","indenfor","vinduet","bliver","afsøgt","daværende","tidspunkt","gør","gennemsnitsdistancer","mellem","hver","farverne","absolutte","forskel","enkelte","komponenter","lægge","dem","sammen","undlader","dog","sammenligne","sig","distancen","ville","være","når","alle","distancerne","fundet","findes","farve","har","mindste","gennemsnitlige","distance","derved","medianvektoren","dét","vindue","denne","vores","dens","indeks","returneret","skrevet","billede-arrayet","plads","evalueret","givende","mere","detaljeret","beskrivelse","kommentarer","koden","derefter","modificeret","bruge","ganske","minimale","ændringer","gjort","splitte","arbejdet","anvender","\\#pragma","angives","variable","bør","private","enkelt","processor","hvis","køres","fås","speed-up","$$668807969","{39195277","\\over","5860468}$$","næsten","gange","hurtigere","derfor","skalerbart","program","udregningen","fra","akkumulerede","udførselstid","henholdsvis","serielle","selvfølgelig","hele","programmets","udførsel","screenshot","kørselstiderne","text]/assets/blog/noise-filtering/consolpng","modefiseret","averagingfilteropenmppixel_array*","pragma","omp","privateij","nm","billederne","fremstår","signifikant","skarpere","brug","vektor","medianmetoden","frem","anvende","metode","benytter","eksempler","forskelige","metoder","text]/assets/blog/noise-filtering/figurpng","også","baggrund","rette","vinduesstørrelse","fx","giver","meget","uskarpt","lig","resultat","man","fik","minimere","artefakterne","artifakter","text]/assets/blog/noise-filtering/figurartifakterpng","post"],"name":"Parallel støj reducerende algoritme"},"rc-car":{"keywords":["hej","post","project","DTU"],"name":"RC Car"},"compiler-f#":{"keywords":["project","consist","designing","high-level","programming","language","called","hygge","implement","compiler","hyggec","implemented","f#","compile","hygge-prgrams","risc-v","assembly","part","construction","dtu","spring","website","found","he[here](https://courses.compute.dtu.dk/02247/f23/overview.html).","skeleton","supplied","start","objective","enhance","incorporating","structures","features","facilitate","development","intricate","programs","accomplish","team","expanded","existing","post","Inovation"],"name":"Design of high-level programming language"},"compiler":{"keywords":["project","consist","designing","high-level","programming","language","called","hygge","implement","compiler","hyggec","implemented","f#","compile","hygge-prgrams","risc-v","assembly","part","construction","dtu","spring","website","found","[here](https://courses.compute.dtu.dk/02247/f23/overview.html).","skeleton","supplied","start","objective","enhance","incorporating","structures","features","facilitate","development","intricate","programs","accomplish","team","expanded","existing","group","blog","post","write","weekly","assignments","code","handel","lexing","parsing","typechecking","generation","optimisation","focus","phase","##","arrays","section","describes","extension","programmers","includes","array","constructor","allocate","memory","run-time","fill","space","allocated","initialization","inputted","programmer","operators","receiving","length","reading","index","writing","specific","position","added","###","extend","function","*docodegen*","**riscvcodegenfs**","adding","case","initialize","checks","requested","size","included","source","main","ends","leaving","address","mentioned","*struct*","*target*","parts","rewritten","constructs","due","time","constraints","```fsharp","|","arraylength","data","->","//","check","bigger","struct","heap","structalloccode","=","beforesyscall","[rega0]","[]","addtext[","rvlirega0","*","amount","{data","length}","bytes","rvlirega7","rars","syscall","sbrk","rvecall","rvmvregrenvtarget","rega0","move","result","mem","target","]","++","aftersyscall","field","lengthcode","asmrvmvregt6","regrenvtarget","adrress","t6","docodegen","env","lengthaddtext[","rvswregrenvtarget","imm124","regt6","rvmvregt4","t4","dataalloccode","load","block","register","a0","rvmulrega0","multiply","+","2u","target+2","store","pointer","datainitcode","asmrvswregrenvtarget","imm120","fieldaddtext[","rvmvregt5","beginlabel","utilgensymbol","loop_begin","codegendata","rvlirega2","element","rvlirega3","starting","addtextrvlabelbeginlabel","rvmulregrenvtarget","rega2","rega3","calculate","offset","base","rvaddregrenvtarget","3u","regt5","rvaddirega3","imm121","increment","rvbltrega3","regt4","loop","ending","]addtextrvcommentallocation","combine","generated","checksize","```","accessing","evaluated","pointing","extracted","arrayelementtarget","///","computes","computed","arrayaccesscode","targetaddtext[","rvlwregrenvtarget","1u","4u","copying","indexcode","envtarget","checklesthenlengthlabel","$index_ok","checklesthenlength","asm[","rvbltregrenvtarget","exit2","assertexitcode","exit","call","rvlabelchecklesthenlengthlabel",">=","checkbiggerthenzerolabel","checkbiggerthenzero","set","a7","rvbgeregrenvtarget","rega7","rvlabelcheckbiggerthenzerolabel","readelment","rvliregt3","regt3","rvaddiregrenvtarget","imm12-4","add","compute","put","input","checked","boundaries","safeguards","built","runtime","determined","out-of-bounds","ensured","performed","order","enable","resolution","dynamically","utilization","**readint**","user","console","program","encounters","error","before-mentioned","rules","violated","**exit2**","$a7","93$","*42*","make","hygge's","test","system","identify","$arraylength$","arraylengthtarget","stored","word","simply","evaluating","results","sub-case","**assign**","assigning","values","report","testing","number","tests","tests/","directory","\\hyggec","examples","picked","%","*030-arrayhyg*","problem","description","difference","defined","*030-array-element-assignhyg*","designed","positions","assigns","asserts","updated","correctly","*029-array-assign-element-out-of-lower-boundhyg*","*029-array-assign-element-out-of-upper-boundhyg*","logic","restricts","inside","works","int","arr","{int}","arrayn","arrayelemarr","int}","array2","assertlen","assertf3","arrayelemarr4","assertarraylengtharr3","string","segment","saved","point","support","comparison","addresses","difficult","$arrayelem$","operator","strings","*assert*","statement","*the","picture","showing","phases","[course","website](https://courses.compute.dtu.dk/02247/f23/overview.html).*","post","project"],"name":"Design of high-level programming language"},"distribueret-galgeleg":{"keywords":["som","en","del","mit","studie","arbejdede","jeg","på","mindre","projekt","hvor","målet","var","udvikle","galgelegs-spil","også","kendt","hangman","engelsk","projektet","blev","udført","af","kursus","om","distribuerede","systemer","vores","underviser","havde","stillet","autentifikationsservice","til","rådighed","så","vi","kunne","logge","ind","med","studienummer","der","service","returnerede","liste","ord","findes","forsiden","drdk","[alt","text]/assets/blog/distribueret-galgeleg/systempng","text]/assets/blog/distribueret-galgeleg/restpng","kurset","fokuserede","give","os","praktisk","erfaring","forskellige","teknologier","brugte","blandt","andet","java's","rmi","kommunikere","autentifikationsserveren","skulle","mindst","grænseflader","spilserveren","og","valgte","lave","rest-interface","soap-interface","udviklet","tui","tekstbaseret","brugergrænseflade","benyttede","soap-interfacet","samt","webgrænseflade","rest-interfacet","skrevet","jquery","text]/assets/blog/distribueret-galgeleg/tuipng","text]/assets/blog/distribueret-galgeleg/loginpng","text]/assets/blog/distribueret-galgeleg/uipng","håndterede","aktive","spil","ved","hashmap","spillere","spilinstanser","alle","vundne","logget","gemt","de","vises","score","board","brugergrænsefladen","text]/assets/blog/distribueret-galgeleg/logpng","post","project"],"name":"Distribueret Galgeleg"},"ga-path-finding":{"keywords":["project","employs","genetic","algorithm","discover","path","starting","point","goal","identified","black","spots","candidate","solutions","represented","colored","circles","begin","moving","randomly","generation","fitness","function","evaluates","performance","rewarding","progress","penalizing","deviations","collisions","obstacles","solution","sequence","movements","two-dimensional","vectors","crossover","combine","mutation","rate","determines","frequently","undergo","crucially","introducing","randomizing","factor","top","population","chosen","tournament","rank","selection","methods","##","initially","move","tendency","upward","movement","deliberate","choice","accelerates","demonstration","showcasing","improvement","rapidly","[alt","text]/assets/blog/ga-path-finding/gif1gif","multiple","generations","typically","12-15","stable","commonly","reached","successfully","navigate","reach","text]/assets/blog/ga-path-finding/gif2gif","developed","blazor","webassembly","application","visualization","rendered","html5","canvas","accessed","[here](https://trolund.github.io/Genetic-algorithm-path-finding/).","post","project"],"name":"Genetic algorithm used for path-finding"},"game-of-life-blazor":{"keywords":["##","introduction","cellular","automata","introduced","john","von","neumann","stanislaw","ulam","subject","extensive","study","fields","including","mathematics","biology","computer","science","game","life","automaton","devised","conway","renowned","simplicity","emergent","complexity","blog","post","presents","blazor","implementation","offering","platform","experimentation","analysis","dynamics","details","utilization","web","framework","microsoft","facilitates","development","interactive","applications","c#","html","users","adjust","size","grid","representing","world","providing","flexibility","random","population","cells","achieved","pseudorandom","number","generation","techniques","ensuring","dynamic","unpredictable","starting","configuration","start","stop","functionality","enables","control","progression","generations","facilitating","observation","customization","features","empower","interactively","modify","clicking","individual","influencing","evolution","patterns","structures","rendering","greatly","improved","utilizing","canvas","future","update","conclusion","serves","academic","exploration","realm","leveraging","capabilities","intuitive","accessible","interface","studying","behaviors","systems","###","references","scientific","american","4-15","retrieved","https://dotnet.microsoft.com/apps/aspnet/web-apps/blazor","post","project"],"name":"Exploring Cellular Automata: A Blazor Implementation of the Game of Life"},"master-thesis":{"keywords":["recently","completed","master","thesis","article","short","overview","primary","goal","design","implement","compiler","capable","generating","valid","webassembly","wasm","code","source","language","hygge","statically","strongly","typed","offers","straightforward","typing","system","subtyping","####","comprehensive","features","implemented","supports","wide","range","making","versatile","powerful","include","-","conditional","statements","pattern","matching","recursive","functions","anonymous","closures","shared","mutable","variables","types","loops","additionally","advanced","data","strings","arrays","structs","top","primitive","integers","floating","points","booleans","#####","program","reads","integer","input","console","computes","nth","term","fibonacci","sequence","function","*fibrec*","result","printed","```hyg","int","=","readint","//","read","define","calculate","fun","fibrecn","{","<=","}","+","print","printlnthe","printlnfibrecn","```","innovative","memory","management","significant","part","dedicated","exploring","multiple","ways","handling","resulting","modes","**embedded","management**","mode","embeds","directly","executable","**external","runtime","implements","logic","external","**wasmgc","extension**","wasmgc","extension","enable","garbage","collection","modern","vm","implementations","flexible","interfaces","introduces","facilitate","i/o","operations","running","host","**wasi","interface**","enables","universally","binaries","**custom","simpler","custom-built","interface","diverse","writing","styles","**simple","linear","style**","approach","**nested","complex","nested","optimization","techniques","efficient","executables","ensure","generated","small","investigated","**local","variable","read-and-write","optimization**","**dead-code","elimination**","**constant","folding**","**branch-level","tree","shaking**","carefully","examined","determine","effectiveness","improving","performance","size","###","conclusion","hyggewasm","represents","advancement","field","generation","supporting","set","offering","providing","implementing","effective","paves","applications","links","entire","found","[here]/assets/docs/thesispdf","*hyggewasm*","[here.](https://github.com/trolund/hyggeWasm)","*learning","development","tool*","debug","programs","[here.](https://github.com/trolund/Wasm-Debugger)","tool","[here.](https://trolund.github.io/Wasm-Debugger)","post","project","DTU"],"name":"A Compiler for Generating WebAssembly (WAT) from the Hygge programing language"},"ba-thesis":{"keywords":["recently","completed","bachelor","handed-in","thesis","post","overview","project","proposed","company","spinoff","consulting","firm","specializing","organizational","leadership","employee","team","development","commissioned","create","performance","evaluation","tool","public","speaking","spectators","provide","feedback","speakers","events","aiding","consultants","offering","improved","advice","guidance","delivered","prototype","system","comprising","net","core","rest","api","backend","nextjs","react","frontend","utilizing","progressive","web","application","pwa","technology","near-native","mobile","experience","focuses","managing","collecting","presenting","concisely","key","features","include","login","user","privileges","administration","real-time","signalr","dashboard","diagram","flow","app","[alt","text]/assets/blog/ba-thesis/1675346501495pdf-image-050png","continuous","integration","deployment","ci/cd","techniques","employed","simplify","management","deployed","azure","testing","production","version","developmentspinoff","###","links","entire","found","[here]/assets/docs/beng-thesispdf","source","code","back-end","[here](https://github.com/trolund/Feedback-Backendv2)","front-end","[here.](https://github.com/trolund/Feedback-PWA)","project","DTU"],"name":"Real-time feedback - Application for optimizing meetings and teaching"},"kalaha-ai":{"keywords":["##","introduction","part","*introduction","artificial","intelligence*","dtu","create","ai","game","choose","classic","board","kalaha","mancala","work","examined","rules","state","space","elements","methods","algorithms","heuristics","parameter","adjustments","benchmarking","results","chosen","deterministic","turn-based","players","complete","visibility","game's","current","starts","setup","meaning","pits","stones","goal","accumulate","store","end","nature","foresee","outcomes","moves","making","excellent","candidate","strategy","development","[alt","text]/assets/blog/kalaha-ai/board_game_assignment_kalahapdf-image-003png","start","shown","console","text]/assets/blog/kalaha-ai/board_game_assignment_kalahapdf-image-005png","complexity","vast","due","numerous","configurations","kalahas","standard","version","including","approximately","\\17","\\times","10^{20}\\","states","unreachable","reducing","practical","\\131","10^{13}\\","reachable","text]/assets/blog/kalaha-ai/board_game_assignment_kalahapdf-image-009png","include","-","**initial","s0**","starting","configuration","pit","**players**","player's","turn","**actionss**","player","**resultss","a**","resulting","action","**terminal-tests**","checks","ended","**eval_win_losss","p**","evaluates","win","loss","draw","**eval_max_difs","measures","favorable","based","score","difference","**eval_sums","assesses","comparing","side","project","implemented","minimax-based","algorithm","alpha-beta","pruning","navigate","tree","efficiently","helps","reduce","number","nodes","evaluated","speeding","decision-making","process","minimax","ability","evaluate","move","exploring","potential","future","tested","determine","effective","**winner","loser","heuristic**","simplistic","focusing","winning","losing","**maximize","point","aiming","maximize","advantage","**sum","considers","sum","predict","losses","gains","testing","heuristic","proved","975%","games","random","agent","ai's","performance","tweaked","parameters","**algorithm","variation**","significantly","reduces","computation","time","compared","**search","depth**","deeper","searches","improving","turn**","significant","leading","playing","optimally","**value","paths**","paths","choosing","path","maximizes","benchmarks","showed","drastically","reduced","search","levels","efficient","choice","implementation","depths","consistently","improved","ensuring","rarely","lost","set","depth","conclusion","demonstrated","application","techniques","solving","combination","resulted","highly","competent","capable","optimal","findings","contribute","understanding","theory","provide","solid","foundation","research","ai-based","strategies","details","view","visit","[github","Repository](https://github.com/trolund/KalahaAI).","full","report","found","[here]/assets/blog/kalaha-ai/board_game_assignment_kalahapdf","contributors","troels","lund","mads","stege","niklas","thielemann","project"],"name":"Exploring AI Strategies in Kalaha"},"recast-earner":{"keywords":["recasttv","offers","paid","content","prefer","spend","program","earn","points","watching","ads","purchase","make","process","easier","created","small","python","script","selenium","automatically","watch","life","earning","running","[recastearner","GitHub](https://github.com/trolund/RecastEarner/blob/master/main.py).","simply","enter","credentials","code","comments","project"],"name":"Earn points on Recast.tv automatically"},"macos-setup":{"keywords":["##","introduction","🧑‍🔬","setting","macos","environment","daunting","task","specific","preferences","suite","applications","rely","daily","luckily","automation","significantly","streamline","process","post","walk","setup","mac","series","scripts","tailor","experience","liking","focusing","efficiency","customization","productivity","*macos*","years+","script","quit","means","perfect","focus","primarily","set","system","software","development","vastly","evolve","time","find","ways","working","###","automate","🤔","automating","benefits","-","**time-saving**","quickly","configure","settings","install","minimal","manual","intervention","**consistency**","ensure","remains","consistent","multiple","devices","**customization**","easily","apply","personalized","fit","workflow","guide","explain","developed","achieve","goals","making","enjoyable","tailored","overview","🗒️","diving","step-by-step","instructions","lets","power","**setup-macossh**","orchestrates","entire","calling","**settings-macossh**","handles","macos-specific","including","dock","configurations","keyboard","trackpad","**utilssh**","utility","functions","managing","*zsh*","configuration","backing","important","files","checking","installations","**shell-setupsh**","customizes","shell","installs","helpful","plugins","enhanced","command-line","**manual-stepsmd**","detailing","steps","needed","complete","handle","automatically","**readmemd**","documentation","explaining","prerequisites","detailed","🪜","dive","follow","step","preparing","🙏","executing","up-to-date","prevent","compatibility","issues","tested","*macos","sonoma","23f79*","running","*install-apps-macossh*","asks","update","orherwise","**system",">","update**","updates","clone","repository","🤟","start","cloning","local","machine","command","terminal","```bash","git","https://github.com/trolund/macos-setup-scripts.git","cd","macos-setup-scripts","```","run","🏃‍♂️","`setup-macossh`","main","entry","point","**please","review","carefully","system**","/setup-macossh","performs","tasks","**configures","settings**","calls","`settings-macossh`","switching","light","dark","mode","customizing","size","behavior","finder","removing","apps","disabling","dashboard","hide","desktop","icons","mush","**installs","applications**","executes","separate","essential","homebrew","includes","tools","nodejs","**sets","shell**","invokes","`shell-setupsh`","themes","customize","🛠","focuses","personalizing","improve","highlights","**appearance","behavior**","switch","based","ambient","magnification","show","hidden","file","extensions","**keyboard","trackpad**","adjust","repeat","rate","faster","typing","enable","tap-to-click","quicker","navigation","**dock","mission","control**","disable","features","cleaner","enhance","🐚","zsh","providing","powerful","flexible","**oh","installation**","popular","framework","**plugin","management**","clones","syntax","highlighting","auto-suggestions","**zsh","configuration**","adds","custom","aliases","variables","usage","😓","adjustments**","fine-tune","notification","privacy","options","**application","manually","require","user","input","email","clients","ides","refer","`manual-stepsmd`","completing","verify","✅","correctly","**test","open","installed","function","expected","**check","confirm","customizations","applied","**explore","terminal**","launch","window","explore","conclusion","🏁","congratulations","successfully","automated","creating","customized","leveraging","scripting","enjoy","seamless","refresh","existing","happy","computing","👨‍💻","post","automation","macOS","productivity"],"name":"Automating Your macOS Setup"},"svg-car-animation":{"keywords":["project","**very","simple","example**","svg","animation","react","component","customizable","renders","animated","car","demonstrating","basic","techniques","animations","including","body","movement","wheel","rotation","vertical","motion","inclusion","clouds","background","[the","GitHub](https://github.com/trolund/car-svg-animation).","[demo","page](https://trolund.github.io/car-svg-animation/).","project"],"name":"Animated SVG Car Component"},"tailwind-tooltip":{"keywords":["comserver","package","definition","requires","shutdown","communication","server","import","post","Inovation"],"name":"Tailwind CSS tooltip"}}